fft/fft64_radix2.v
`timescale 1ns/1ps

module fft64_radix2 #(
    parameter DATA_W = 32,
    parameter TW_W   = 16
)(
    input  wire clk,
    input  wire rst,
    input  wire start,

    input  wire signed [DATA_W-1:0] in_real [0:63],
    input  wire signed [DATA_W-1:0] in_imag [0:63],

    output reg signed [DATA_W-1:0] out_real [0:63],
    output reg signed [DATA_W-1:0] out_imag [0:63],

    output reg done
);

    // ============================================================
    // FFT DATA MEMORY
    // ============================================================

    reg signed [DATA_W-1:0] real_mem [0:63];
    reg signed [DATA_W-1:0] imag_mem [0:63];


    // ============================================================
    // TWIDDLE FACTORS
    //
    // W64^k = cos(2*pi*k/64) - j*sin(2*pi*k/64)
    //
    // Format Q1.15
    // ============================================================

    reg signed [TW_W-1:0] tw_real [0:31];
    reg signed [TW_W-1:0] tw_imag [0:31];

    initial begin

        tw_real[0]  =  32767;
        tw_imag[0]  =      0;

        tw_real[1]  =  32610;
        tw_imag[1]  =  -3212;

        tw_real[2]  =  32138;
        tw_imag[2]  =  -6393;

        tw_real[3]  =  31357;
        tw_imag[3]  =  -9512;

        tw_real[4]  =  30273;
        tw_imag[4]  = -12539;

        tw_real[5]  =  28898;
        tw_imag[5]  = -15446;

        tw_real[6]  =  27245;
        tw_imag[6]  = -18204;

        tw_real[7]  =  25329;
        tw_imag[7]  = -20854;

        tw_real[8]  =  23170;
        tw_imag[8]  = -23170;

        tw_real[9]  =  20854;
        tw_imag[9]  = -25329;

        tw_real[10] =  18204;
        tw_imag[10] = -27245;

        tw_real[11] =  15446;
        tw_imag[11] = -28898;

        tw_real[12] =  12539;
        tw_imag[12] = -30273;

        tw_real[13] =   9512;
        tw_imag[13] = -31357;

        tw_real[14] =   6393;
        tw_imag[14] = -32138;

        tw_real[15] =   3212;
        tw_imag[15] = -32610;

        tw_real[16] =      0;
        tw_imag[16] = -32768;

        tw_real[17] =  -3212;
        tw_imag[17] = -32610;

        tw_real[18] =  -6393;
        tw_imag[18] = -32138;

        tw_real[19] =  -9512;
        tw_imag[19] = -31357;

        tw_real[20] = -12539;
        tw_imag[20] = -30273;

        tw_real[21] = -15446;
        tw_imag[21] = -28898;

        tw_real[22] = -18204;
        tw_imag[22] = -27245;

        tw_real[23] = -20854;
        tw_imag[23] = -25329;

        tw_real[24] = -23170;
        tw_imag[24] = -23170;

        tw_real[25] = -25329;
        tw_imag[25] = -20854;

        tw_real[26] = -27245;
        tw_imag[26] = -18204;

        tw_real[27] = -28898;
        tw_imag[27] = -15446;

        tw_real[28] = -30273;
        tw_imag[28] = -12539;

        tw_real[29] = -31357;
        tw_imag[29] =  -9512;

        tw_real[30] = -32138;
        tw_imag[30] =  -6393;

        tw_real[31] = -32610;
        tw_imag[31] =  -3212;

    end


    // ============================================================
    // BIT REVERSAL
    //
    // 64 point -> 6 bit address
    // ============================================================

    function [5:0] bit_reverse;
        input [5:0] x;

        begin
            bit_reverse[5] = x[0];
            bit_reverse[4] = x[1];
            bit_reverse[3] = x[2];
            bit_reverse[2] = x[3];
            bit_reverse[1] = x[4];
            bit_reverse[0] = x[5];
        end

    endfunction


    // ============================================================
    // FFT STAGE TASK
    //
    // stage 0:
    //   butterfly size = 2
    //
    // stage 1:
    //   butterfly size = 4
    //
    // ...
    //
    // stage 5:
    //   butterfly size = 64
    // ============================================================

    task automatic do_stage;

        input integer stage_number;

        integer half_size;
        integer step_size;
        integer tw_step;

        integer group;
        integer k;

        integer i0;
        integer i1;
        integer tw_idx;

        reg signed [DATA_W-1:0] ar;
        reg signed [DATA_W-1:0] ai;

        reg signed [DATA_W-1:0] br;
        reg signed [DATA_W-1:0] bi;

        reg signed [TW_W-1:0] wr;
        reg signed [TW_W-1:0] wi;

        // Product width:
        // DATA_W + TW_W = 48 bit for 32x16

        reg signed [DATA_W+TW_W-1:0] p_rr;
        reg signed [DATA_W+TW_W-1:0] p_ii;
        reg signed [DATA_W+TW_W-1:0] p_ri;
        reg signed [DATA_W+TW_W-1:0] p_ir;

        reg signed [DATA_W+TW_W-1:0] temp_real;
        reg signed [DATA_W+TW_W-1:0] temp_imag;

        // Explicitly reduced back to DATA_W
        reg signed [DATA_W-1:0] vr;
        reg signed [DATA_W-1:0] vi;

        reg signed [DATA_W-1:0] sum_real;
        reg signed [DATA_W-1:0] sum_imag;

        reg signed [DATA_W-1:0] diff_real;
        reg signed [DATA_W-1:0] diff_imag;

        begin

            // ----------------------------------------------------
            // FFT parameters
            // ----------------------------------------------------

            half_size = 1 << stage_number;
            step_size = half_size << 1;
            tw_step   = 64 / step_size;


            // ----------------------------------------------------
            // 32 butterflies per stage
            // ----------------------------------------------------

            for (group = 0;
                 group < (64 / step_size);
                 group = group + 1) begin

                for (k = 0;
                     k < half_size;
                     k = k + 1) begin

                    // Butterfly input addresses

                    i0 = group * step_size + k;
                    i1 = i0 + half_size;

                    // Twiddle index

                    tw_idx = k * tw_step;


                    // ------------------------------------------------
                    // Read input
                    // ------------------------------------------------

                    ar = real_mem[i0];
                    ai = imag_mem[i0];

                    br = real_mem[i1];
                    bi = imag_mem[i1];


                    // ------------------------------------------------
                    // Read twiddle
                    // ------------------------------------------------

                    wr = tw_real[tw_idx];
                    wi = tw_imag[tw_idx];


                    // ------------------------------------------------
                    // Complex multiplication
                    //
                    // (br + jbi)(wr + jwi)
                    //
                    // real = br*wr - bi*wi
                    // imag = br*wi + bi*wr
                    // ------------------------------------------------

                    p_rr = br * wr;
                    p_ii = bi * wi;

                    p_ri = br * wi;
                    p_ir = bi * wr;

                    temp_real = (p_rr - p_ii) >>> 15;
                    temp_imag = (p_ri + p_ir) >>> 15;


                    // ------------------------------------------------
                    // Explicit 32-bit conversion
                    //
                    // Prevents Verilator width warnings.
                    // ------------------------------------------------

                    vr = temp_real[DATA_W-1:0];
                    vi = temp_imag[DATA_W-1:0];


                    // ------------------------------------------------
                    // Radix-2 butterfly
                    //
                    // X0 = A + B
                    // X1 = A - B
                    // ------------------------------------------------

                    sum_real  = ar + vr;
                    sum_imag  = ai + vi;

                    diff_real = ar - vr;
                    diff_imag = ai - vi;


                    // ------------------------------------------------
                    // Write butterfly result
                    // ------------------------------------------------

                    real_mem[i0] <= sum_real;
                    imag_mem[i0] <= sum_imag;

                    real_mem[i1] <= diff_real;
                    imag_mem[i1] <= diff_imag;

                end

            end

        end

    endtask


    // ============================================================
    // FSM
    // ============================================================

    localparam STATE_IDLE   = 4'd0;
    localparam STATE_LOAD   = 4'd1;
    localparam STATE_STAGE0 = 4'd2;
    localparam STATE_STAGE1 = 4'd3;
    localparam STATE_STAGE2 = 4'd4;
    localparam STATE_STAGE3 = 4'd5;
    localparam STATE_STAGE4 = 4'd6;
    localparam STATE_STAGE5 = 4'd7;
    localparam STATE_OUTPUT = 4'd8;
    localparam STATE_DONE   = 4'd9;

    reg [3:0] state;

    integer n;

    reg [5:0] load_index;


    // ============================================================
    // MAIN FSM
    // ============================================================

    always @(posedge clk) begin

        if (rst) begin

            state <= STATE_IDLE;
            done  <= 1'b0;

            load_index <= 6'd0;

            for (n = 0; n < 64; n = n + 1) begin

                real_mem[n] <= '0;
                imag_mem[n] <= '0;

                out_real[n] <= '0;
                out_imag[n] <= '0;

            end

        end
        else begin

            case (state)

                // ==================================================
                // IDLE
                // ==================================================

                STATE_IDLE: begin

                    done <= 1'b0;

                    if (start) begin
                        state <= STATE_LOAD;
                    end

                end


                // ==================================================
                // LOAD
                //
                // Input -> bit reversed memory
                // ==================================================

                STATE_LOAD: begin

    for (n = 0; n < 64; n = n + 1) begin

        real_mem[bit_reverse(n[5:0])]
            <= in_real[n];

        imag_mem[bit_reverse(n[5:0])]
            <= in_imag[n];

    end

    state <= STATE_STAGE0;

end


                // ==================================================
                // STAGE 0
                // ==================================================

                STATE_STAGE0: begin

                    do_stage(0);

                    state <= STATE_STAGE1;

                end


                // ==================================================
                // STAGE 1
                // ==================================================

                STATE_STAGE1: begin

                    do_stage(1);

                    state <= STATE_STAGE2;

                end


                // ==================================================
                // STAGE 2
                // ==================================================

                STATE_STAGE2: begin

                    do_stage(2);

                    state <= STATE_STAGE3;

                end


                // ==================================================
                // STAGE 3
                // ==================================================

                STATE_STAGE3: begin

                    do_stage(3);

                    state <= STATE_STAGE4;

                end


                // ==================================================
                // STAGE 4
                // ==================================================

                STATE_STAGE4: begin

                    do_stage(4);

                    state <= STATE_STAGE5;

                end


                // ==================================================
                // STAGE 5
                // ==================================================

                STATE_STAGE5: begin

                    do_stage(5);

                    state <= STATE_OUTPUT;

                end


                // ==================================================
                // OUTPUT
                //
                // Separate state is important:
                //
                // STAGE5 writes real_mem/imag_mem using NBA.
                // Therefore output must be copied on the NEXT clock.
                // ==================================================

                STATE_OUTPUT: begin

                    for (n = 0; n < 64; n = n + 1) begin

                        out_real[n] <= real_mem[n];
                        out_imag[n] <= imag_mem[n];

                    end

                    state <= STATE_DONE;

                end


                // ==================================================
                // DONE
                // ==================================================

                STATE_DONE: begin

                    done <= 1'b1;

                    state <= STATE_IDLE;

                end


                // ==================================================
                // DEFAULT
                // ==================================================

                default: begin

                    state <= STATE_IDLE;
                    done  <= 1'b0;

                end

            endcase

        end

    end

endmodule

fft/tb_fft64.v
`timescale 1ns/1ps

module tb_fft64;

    parameter DATA_W = 32;

    // ============================================================
    // Clock / reset
    // ============================================================

    reg clk;
    reg rst;
    reg start;

    // ============================================================
    // FFT input
    // ============================================================

    reg signed [DATA_W-1:0] in_real [0:63];
    reg signed [DATA_W-1:0] in_imag [0:63];

    // ============================================================
    // FFT output
    // ============================================================

    wire signed [DATA_W-1:0] out_real [0:63];
    wire signed [DATA_W-1:0] out_imag [0:63];

    wire done;


    // ============================================================
    // DUT
    // ============================================================

    fft64_radix2 #(
        .DATA_W(DATA_W),
        .TW_W(16)
    ) dut (

        .clk(clk),
        .rst(rst),
        .start(start),

        .in_real(in_real),
        .in_imag(in_imag),

        .out_real(out_real),
        .out_imag(out_imag),

        .done(done)

    );


    // ============================================================
    // Clock
    //
    // 10 ns period = 100 MHz
    // ============================================================

    initial begin

        clk = 1'b0;

        forever #5 clk = ~clk;

    end


    // ============================================================
    // Generate test signal
    //
    // 64-point sine wave
    //
    // FFT bin = 4
    //
    // x[n] = 12000 sin(2*pi*4*n/64)
    // ============================================================

    integer n;

    real pi;
    real angle;
    real sample;

    initial begin

        pi = 3.14159265358979323846;

        for (n = 0; n < 64; n = n + 1) begin

            angle  = 2.0 * pi * 4.0 * n / 64.0;
            sample = 12000.0 * $sin(angle);

            in_real[n] = $rtoi(sample);
            in_imag[n] = 0;

        end

    end


    // ============================================================
    // Test sequence
    // ============================================================

    initial begin

        // VCD
        $dumpfile("fft64.vcd");
        $dumpvars(0, tb_fft64);

        // Initial values
        rst   = 1'b1;
        start = 1'b0;

        // Reset
        #20;

        rst = 1'b0;

        #20;

        // Start FFT
        $display("");
        $display("==============================================");
        $display("64-POINT RADIX-2 FFT");
        $display("==============================================");

        $display("");
        $display("INPUT SIGNAL:");
        $display("x[n] = 12000*sin(2*pi*4*n/64)");
        $display("Expected FFT peaks: bin 4 and bin 60");
        $display("");

        for (n = 0; n < 64; n = n + 1) begin

            $display(
                "input[%2d] = %8d + j%8d",
                n,
                in_real[n],
                in_imag[n]
            );

        end

        // --------------------------------------------------------
        // Start pulse
        // --------------------------------------------------------

        @(posedge clk);

        start <= 1'b1;

        @(posedge clk);

        start <= 1'b0;

        $display("");
        $display("FFT STARTED...");
        $display("");

        // --------------------------------------------------------
        // Wait for FFT
        // --------------------------------------------------------

        wait(done == 1'b1);

        @(posedge clk);

        // --------------------------------------------------------
        // Print output
        // --------------------------------------------------------

        $display("");
        $display("==============================================");
        $display("FFT RESULT");
        $display("==============================================");

        for (n = 0; n < 64; n = n + 1) begin

            $display(
                "X[%2d] = %12d + j%12d",
                n,
                out_real[n],
                out_imag[n]
            );

        end

        $display("");
        $display("==============================================");
        $display("EXPECTED:");
        $display("Large peak around bin 4");
        $display("Large peak around bin 60");
        $display("==============================================");
        $display("");

        #20;

        $finish;

    end

endmodule

fft/fft64.vcd
$version Generated by VerilatedVcd $end
$timescale 1ps $end
 $scope module tb_fft64 $end
  $var wire 32 p DATA_W [31:0] $end
  $var wire 1 l clk $end
  $var wire 1 m rst $end
  $var wire 1 n start $end
  $var wire 1 h done $end
  $var wire 32 o n [31:0] $end
  $var real 64 " pi $end
  $var real 64 $ angle $end
  $var real 64 & sample $end
  $scope module dut $end
   $var wire 32 p DATA_W [31:0] $end
   $var wire 32 q TW_W [31:0] $end
   $var wire 1 l clk $end
   $var wire 1 m rst $end
   $var wire 1 n start $end
   $var wire 1 h done $end
   $var wire 16 ( tw_real[0] [15:0] $end
   $var wire 16 ) tw_real[1] [15:0] $end
   $var wire 16 * tw_real[2] [15:0] $end
   $var wire 16 + tw_real[3] [15:0] $end
   $var wire 16 , tw_real[4] [15:0] $end
   $var wire 16 - tw_real[5] [15:0] $end
   $var wire 16 . tw_real[6] [15:0] $end
   $var wire 16 / tw_real[7] [15:0] $end
   $var wire 16 0 tw_real[8] [15:0] $end
   $var wire 16 1 tw_real[9] [15:0] $end
   $var wire 16 2 tw_real[10] [15:0] $end
   $var wire 16 3 tw_real[11] [15:0] $end
   $var wire 16 4 tw_real[12] [15:0] $end
   $var wire 16 5 tw_real[13] [15:0] $end
   $var wire 16 6 tw_real[14] [15:0] $end
   $var wire 16 7 tw_real[15] [15:0] $end
   $var wire 16 8 tw_real[16] [15:0] $end
   $var wire 16 9 tw_real[17] [15:0] $end
   $var wire 16 : tw_real[18] [15:0] $end
   $var wire 16 ; tw_real[19] [15:0] $end
   $var wire 16 < tw_real[20] [15:0] $end
   $var wire 16 = tw_real[21] [15:0] $end
   $var wire 16 > tw_real[22] [15:0] $end
   $var wire 16 ? tw_real[23] [15:0] $end
   $var wire 16 @ tw_real[24] [15:0] $end
   $var wire 16 A tw_real[25] [15:0] $end
   $var wire 16 B tw_real[26] [15:0] $end
   $var wire 16 C tw_real[27] [15:0] $end
   $var wire 16 D tw_real[28] [15:0] $end
   $var wire 16 E tw_real[29] [15:0] $end
   $var wire 16 F tw_real[30] [15:0] $end
   $var wire 16 G tw_real[31] [15:0] $end
   $var wire 16 H tw_imag[0] [15:0] $end
   $var wire 16 I tw_imag[1] [15:0] $end
   $var wire 16 J tw_imag[2] [15:0] $end
   $var wire 16 K tw_imag[3] [15:0] $end
   $var wire 16 L tw_imag[4] [15:0] $end
   $var wire 16 M tw_imag[5] [15:0] $end
   $var wire 16 N tw_imag[6] [15:0] $end
   $var wire 16 O tw_imag[7] [15:0] $end
   $var wire 16 P tw_imag[8] [15:0] $end
   $var wire 16 Q tw_imag[9] [15:0] $end
   $var wire 16 R tw_imag[10] [15:0] $end
   $var wire 16 S tw_imag[11] [15:0] $end
   $var wire 16 T tw_imag[12] [15:0] $end
   $var wire 16 U tw_imag[13] [15:0] $end
   $var wire 16 V tw_imag[14] [15:0] $end
   $var wire 16 W tw_imag[15] [15:0] $end
   $var wire 16 X tw_imag[16] [15:0] $end
   $var wire 16 Y tw_imag[17] [15:0] $end
   $var wire 16 Z tw_imag[18] [15:0] $end
   $var wire 16 [ tw_imag[19] [15:0] $end
   $var wire 16 \ tw_imag[20] [15:0] $end
   $var wire 16 ] tw_imag[21] [15:0] $end
   $var wire 16 ^ tw_imag[22] [15:0] $end
   $var wire 16 _ tw_imag[23] [15:0] $end
   $var wire 16 ` tw_imag[24] [15:0] $end
   $var wire 16 a tw_imag[25] [15:0] $end
   $var wire 16 b tw_imag[26] [15:0] $end
   $var wire 16 c tw_imag[27] [15:0] $end
   $var wire 16 d tw_imag[28] [15:0] $end
   $var wire 16 e tw_imag[29] [15:0] $end
   $var wire 16 f tw_imag[30] [15:0] $end
   $var wire 16 g tw_imag[31] [15:0] $end
   $var wire 4 r STATE_IDLE [3:0] $end
   $var wire 4 s STATE_LOAD [3:0] $end
   $var wire 4 t STATE_STAGE0 [3:0] $end
   $var wire 4 u STATE_STAGE1 [3:0] $end
   $var wire 4 v STATE_STAGE2 [3:0] $end
   $var wire 4 w STATE_STAGE3 [3:0] $end
   $var wire 4 x STATE_STAGE4 [3:0] $end
   $var wire 4 y STATE_STAGE5 [3:0] $end
   $var wire 4 z STATE_OUTPUT [3:0] $end
   $var wire 4 { STATE_DONE [3:0] $end
   $var wire 4 i state [3:0] $end
   $var wire 32 j n [31:0] $end
   $var wire 6 k load_index [5:0] $end
  $upscope $end
 $upscope $end
$enddefinitions $end


#0
r3.141592653589793 "
r24.74004214701962 $
r-4592.201188381074 &
b0111111111111111 (
b0111111101100010 )
b0111110110001010 *
b0111101001111101 +
b0111011001000001 ,
b0111000011100010 -
b0110101001101101 .
b0110001011110001 /
b0101101010000010 0
b0101000101110110 1
b0100011100011100 2
b0011110001010110 3
b0011000011111011 4
b0010010100101000 5
b0001100011111001 6
b0000110010001100 7
b0000000000000000 8
b1111001101110100 9
b1110011100000111 :
b1101101011011000 ;
b1100111100000101 <
b1100001110101010 =
b1011100011100100 >
b1010111010001010 ?
b1010010101111110 @
b1001110100001111 A
b1001010110010011 B
b1000111100011110 C
b1000100110111111 D
b1000010110000011 E
b1000001001110110 F
b1000000010011110 G
b0000000000000000 H
b1111001101110100 I
b1110011100000111 J
b1101101011011000 K
b1100111100000101 L
b1100001110101010 M
b1011100011100100 N
b1010111010001010 O
b1010010101111110 P
b1001110100001111 Q
b1001010110010011 R
b1000111100011110 S
b1000100110111111 T
b1000010110000011 U
b1000001001110110 V
b1000000010011110 W
b1000000000000000 X
b1000000010011110 Y
b1000001001110110 Z
b1000010110000011 [
b1000100110111111 \
b1000111100011110 ]
b1001010110010011 ^
b1001110100001111 _
b1010010101111110 `
b1010111010001010 a
b1011100011100100 b
b1100001110101010 c
b1100111100000101 d
b1101101011011000 e
b1110011100000111 f
b1111001101110100 g
0h
b0000 i
b00000000000000000000000000000000 j
b000000 k
0l
1m
0n
b00000000000000000000000001000000 o
b00000000000000000000000000100000 p
b00000000000000000000000000010000 q
b0000 r
b0001 s
b0010 t
b0011 u
b0100 v
b0101 w
b0110 x
b0111 y
b1000 z
b1001 {
#5000
b00000000000000000000000001000000 j
1l
#10000
0l
#15000
1l
#20000
0l
0m
#25000
1l
#30000
0l
#35000
1l
#40000
0l
#45000
1l
1n
#50000
0l
#55000
b0001 i
1l
0n
#60000
0l
#65000
b0010 i
1l
#70000
0l
#75000
b0011 i
1l
#80000
0l
#85000
b0100 i
1l
#90000
0l
#95000
b0101 i
1l
#100000
0l
#105000
b0110 i
1l
#110000
0l
#115000
b0111 i
1l
#120000
0l
#125000
b1000 i
1l
#130000
0l
#135000
b1001 i
1l
#140000
0l
#145000
1h
b0000 i
1l
#150000
0l
#155000
0h
1l
