fft/fft8.v
`timescale 1ns/1ps

module fft8 (
    input  wire clk,
    input  wire reset,
    input  wire start,

    input  wire signed [15:0] x0,
    input  wire signed [15:0] x1,
    input  wire signed [15:0] x2,
    input  wire signed [15:0] x3,
    input  wire signed [15:0] x4,
    input  wire signed [15:0] x5,
    input  wire signed [15:0] x6,
    input  wire signed [15:0] x7,

    output reg signed [31:0] y0_re,
    output reg signed [31:0] y1_re,
    output reg signed [31:0] y2_re,
    output reg signed [31:0] y3_re,
    output reg signed [31:0] y4_re,
    output reg signed [31:0] y5_re,
    output reg signed [31:0] y6_re,
    output reg signed [31:0] y7_re,

    output reg signed [31:0] y0_im,
    output reg signed [31:0] y1_im,
    output reg signed [31:0] y2_im,
    output reg signed [31:0] y3_im,
    output reg signed [31:0] y4_im,
    output reg signed [31:0] y5_im,
    output reg signed [31:0] y6_im,
    output reg signed [31:0] y7_im,

    output reg done
);

    // =========================================================
    // FSM
    // =========================================================

    localparam IDLE   = 3'd0;
    localparam LOAD   = 3'd1;
    localparam STAGE1 = 3'd2;
    localparam STAGE2 = 3'd3;
    localparam STAGE3 = 3'd4;
    localparam OUTPUT = 3'd5;

    reg [2:0] state;


    // =========================================================
    // FFT stage memories
    // =========================================================

    reg signed [31:0] s0_re [0:7];
    reg signed [31:0] s0_im [0:7];

    reg signed [31:0] s1_re [0:7];
    reg signed [31:0] s1_im [0:7];

    reg signed [31:0] s2_re [0:7];
    reg signed [31:0] s2_im [0:7];

    reg signed [31:0] s3_re [0:7];
    reg signed [31:0] s3_im [0:7];


    // =========================================================
    // Twiddle factors Q1.15
    // =========================================================

    localparam signed [15:0] W1_RE = 16'sd23170;
    localparam signed [15:0] W1_IM = -16'sd23170;

    localparam signed [15:0] W2_RE = 16'sd0;
    localparam signed [15:0] W2_IM = -16'sd32767;

    localparam signed [15:0] W3_RE = -16'sd23170;
    localparam signed [15:0] W3_IM = -16'sd23170;


    // =========================================================
    // Temporary multiplication variables
    // =========================================================

    reg signed [63:0] mult_re;
    reg signed [63:0] mult_im;

    reg signed [31:0] tw_re;
    reg signed [31:0] tw_im;


    integer i;


    // =========================================================
    // Main FSM
    // =========================================================

    always @(posedge clk) begin

        if (reset) begin

            state <= IDLE;
            done  <= 1'b0;

            y0_re <= 0;
            y1_re <= 0;
            y2_re <= 0;
            y3_re <= 0;
            y4_re <= 0;
            y5_re <= 0;
            y6_re <= 0;
            y7_re <= 0;

            y0_im <= 0;
            y1_im <= 0;
            y2_im <= 0;
            y3_im <= 0;
            y4_im <= 0;
            y5_im <= 0;
            y6_im <= 0;
            y7_im <= 0;

            for (i = 0; i < 8; i = i + 1) begin

                s0_re[i] <= 0;
                s0_im[i] <= 0;

                s1_re[i] <= 0;
                s1_im[i] <= 0;

                s2_re[i] <= 0;
                s2_im[i] <= 0;

                s3_re[i] <= 0;
                s3_im[i] <= 0;

            end

        end else begin

            done <= 1'b0;

            case (state)

                // =================================================
                // IDLE
                // =================================================

                IDLE: begin

                    if (start)
                        state <= LOAD;

                end


                // =================================================
                // LOAD + BIT REVERSE
                //
                // Natural input:
                //
                // x0 x1 x2 x3 x4 x5 x6 x7
                //
                // Bit reversed:
                //
                // x0 x4 x2 x6 x1 x5 x3 x7
                // =================================================

                LOAD: begin

                    s0_re[0] <= {{16{x0[15]}}, x0};
s0_re[1] <= {{16{x4[15]}}, x4};
s0_re[2] <= {{16{x2[15]}}, x2};
s0_re[3] <= {{16{x6[15]}}, x6};
s0_re[4] <= {{16{x1[15]}}, x1};
s0_re[5] <= {{16{x5[15]}}, x5};
s0_re[6] <= {{16{x3[15]}}, x3};
s0_re[7] <= {{16{x7[15]}}, x7};

                    s0_im[0] <= 0;
                    s0_im[1] <= 0;
                    s0_im[2] <= 0;
                    s0_im[3] <= 0;
                    s0_im[4] <= 0;
                    s0_im[5] <= 0;
                    s0_im[6] <= 0;
                    s0_im[7] <= 0;

                    state <= STAGE1;

                end


                // =================================================
                // STAGE 1
                //
                // 2-point butterflies
                // =================================================

                STAGE1: begin

                    // butterfly 0
                    s1_re[0] <= s0_re[0] + s0_re[1];
                    s1_im[0] <= s0_im[0] + s0_im[1];

                    s1_re[1] <= s0_re[0] - s0_re[1];
                    s1_im[1] <= s0_im[0] - s0_im[1];


                    // butterfly 1
                    s1_re[2] <= s0_re[2] + s0_re[3];
                    s1_im[2] <= s0_im[2] + s0_im[3];

                    s1_re[3] <= s0_re[2] - s0_re[3];
                    s1_im[3] <= s0_im[2] - s0_im[3];


                    // butterfly 2
                    s1_re[4] <= s0_re[4] + s0_re[5];
                    s1_im[4] <= s0_im[4] + s0_im[5];

                    s1_re[5] <= s0_re[4] - s0_re[5];
                    s1_im[5] <= s0_im[4] - s0_im[5];


                    // butterfly 3
                    s1_re[6] <= s0_re[6] + s0_re[7];
                    s1_im[6] <= s0_im[6] + s0_im[7];

                    s1_re[7] <= s0_re[6] - s0_re[7];
                    s1_im[7] <= s0_im[6] - s0_im[7];

                    state <= STAGE2;

                end


                // =================================================
                // STAGE 2
                //
                // 4-point butterflies
                // =================================================

                STAGE2: begin

                    // ---------------------------------------------
                    // First 4-point FFT
                    // ---------------------------------------------

                    // k = 0
                    s2_re[0] <= s1_re[0] + s1_re[2];
                    s2_im[0] <= s1_im[0] + s1_im[2];

                    s2_re[2] <= s1_re[0] - s1_re[2];
                    s2_im[2] <= s1_im[0] - s1_im[2];


                    // k = 1
                    // Multiply by -j
                    s2_re[1] <= s1_re[1] + s1_im[3];
                    s2_im[1] <= s1_im[1] - s1_re[3];

                    s2_re[3] <= s1_re[1] - s1_im[3];
                    s2_im[3] <= s1_im[1] + s1_re[3];


                    // ---------------------------------------------
                    // Second 4-point FFT
                    // ---------------------------------------------

                    s2_re[4] <= s1_re[4] + s1_re[6];
                    s2_im[4] <= s1_im[4] + s1_im[6];

                    s2_re[6] <= s1_re[4] - s1_re[6];
                    s2_im[6] <= s1_im[4] - s1_im[6];


                    s2_re[5] <= s1_re[5] + s1_im[7];
                    s2_im[5] <= s1_im[5] - s1_re[7];

                    s2_re[7] <= s1_re[5] - s1_im[7];
                    s2_im[7] <= s1_im[5] + s1_re[7];

                    state <= STAGE3;

                end


                // =================================================
                // STAGE 3
                //
                // 8-point FFT
                // =================================================

                STAGE3: begin

                    // ---------------------------------------------
                    // k = 0
                    // W8^0 = 1
                    // ---------------------------------------------

                    s3_re[0] <= s2_re[0] + s2_re[4];
                    s3_im[0] <= s2_im[0] + s2_im[4];

                    s3_re[4] <= s2_re[0] - s2_re[4];
                    s3_im[4] <= s2_im[0] - s2_im[4];


                    // ---------------------------------------------
                    // k = 1
                    // W8^1 = 0.707 - j0.707
                    // ---------------------------------------------

                    mult_re =
                        (s2_re[5] * W1_RE) -
                        (s2_im[5] * W1_IM);

                    mult_im =
                        (s2_re[5] * W1_IM) +
                        (s2_im[5] * W1_RE);

                   tw_re = $signed(mult_re[46:15]);
tw_im = $signed(mult_im[46:15]);

                    s3_re[1] <= s2_re[1] + tw_re;
                    s3_im[1] <= s2_im[1] + tw_im;

                    s3_re[5] <= s2_re[1] - tw_re;
                    s3_im[5] <= s2_im[1] - tw_im;


                    // ---------------------------------------------
                    // k = 2
                    // W8^2 = -j
                    // ---------------------------------------------

                    tw_re = s2_im[6];
                    tw_im = -s2_re[6];

                    s3_re[2] <= s2_re[2] + tw_re;
                    s3_im[2] <= s2_im[2] + tw_im;

                    s3_re[6] <= s2_re[2] - tw_re;
                    s3_im[6] <= s2_im[2] - tw_im;


                    // ---------------------------------------------
                    // k = 3
                    // W8^3 = -0.707 - j0.707
                    // ---------------------------------------------

                    mult_re =
                        (s2_re[7] * W3_RE) -
                        (s2_im[7] * W3_IM);

                    mult_im =
                        (s2_re[7] * W3_IM) +
                        (s2_im[7] * W3_RE);

                   tw_re = $signed(mult_re[46:15]);
tw_im = $signed(mult_im[46:15]);

                    s3_re[3] <= s2_re[3] + tw_re;
                    s3_im[3] <= s2_im[3] + tw_im;

                    s3_re[7] <= s2_re[3] - tw_re;
                    s3_im[7] <= s2_im[3] - tw_im;

                    state <= OUTPUT;

                end


                // =================================================
                // OUTPUT
                // =================================================

                OUTPUT: begin

                    y0_re <= s3_re[0];
                    y1_re <= s3_re[1];
                    y2_re <= s3_re[2];
                    y3_re <= s3_re[3];
                    y4_re <= s3_re[4];
                    y5_re <= s3_re[5];
                    y6_re <= s3_re[6];
                    y7_re <= s3_re[7];

                    y0_im <= s3_im[0];
                    y1_im <= s3_im[1];
                    y2_im <= s3_im[2];
                    y3_im <= s3_im[3];
                    y4_im <= s3_im[4];
                    y5_im <= s3_im[5];
                    y6_im <= s3_im[6];
                    y7_im <= s3_im[7];

                    done <= 1'b1;

                    state <= IDLE;

                end


                default: begin
                    state <= IDLE;
                end

            endcase

        end

    end

endmodule

fft/tb_fft8.v
`timescale 1ns/1ps

module tb_fft8;

    reg clk;
    reg reset;
    reg start;

    reg signed [15:0] x0;
    reg signed [15:0] x1;
    reg signed [15:0] x2;
    reg signed [15:0] x3;
    reg signed [15:0] x4;
    reg signed [15:0] x5;
    reg signed [15:0] x6;
    reg signed [15:0] x7;

    wire signed [31:0] y0_re;
    wire signed [31:0] y1_re;
    wire signed [31:0] y2_re;
    wire signed [31:0] y3_re;
    wire signed [31:0] y4_re;
    wire signed [31:0] y5_re;
    wire signed [31:0] y6_re;
    wire signed [31:0] y7_re;

    wire signed [31:0] y0_im;
    wire signed [31:0] y1_im;
    wire signed [31:0] y2_im;
    wire signed [31:0] y3_im;
    wire signed [31:0] y4_im;
    wire signed [31:0] y5_im;
    wire signed [31:0] y6_im;
    wire signed [31:0] y7_im;

    wire done;


    // =========================================================
    // DUT
    // =========================================================

    fft8 dut (
        .clk(clk),
        .reset(reset),
        .start(start),

        .x0(x0),
        .x1(x1),
        .x2(x2),
        .x3(x3),
        .x4(x4),
        .x5(x5),
        .x6(x6),
        .x7(x7),

        .y0_re(y0_re),
        .y1_re(y1_re),
        .y2_re(y2_re),
        .y3_re(y3_re),
        .y4_re(y4_re),
        .y5_re(y5_re),
        .y6_re(y6_re),
        .y7_re(y7_re),

        .y0_im(y0_im),
        .y1_im(y1_im),
        .y2_im(y2_im),
        .y3_im(y3_im),
        .y4_im(y4_im),
        .y5_im(y5_im),
        .y6_im(y6_im),
        .y7_im(y7_im),

        .done(done)
    );


    // =========================================================
    // Clock
    // =========================================================

    always #5 clk = ~clk;


    // =========================================================
    // Simulation
    // =========================================================

    initial begin

        $dumpfile("fft8.vcd");
        $dumpvars(0, tb_fft8);

        clk   = 1'b0;
        reset = 1'b1;
        start = 1'b0;

        // Impulse input
        x0 = 16'sd1;
        x1 = 16'sd0;
        x2 = 16'sd0;
        x3 = 16'sd0;
        x4 = 16'sd0;
        x5 = 16'sd0;
        x6 = 16'sd0;
        x7 = 16'sd0;

        // Reset
        #20;

        reset = 1'b0;

        // Start FFT
        #10;
        start = 1'b1;

        #10;
        start = 1'b0;

        // Wait
        #100;

        $display("");
        $display("======================================");
        $display("             FFT-8 TEST");
        $display("======================================");

        $display("X[0] = %0d + j(%0d)", y0_re, y0_im);
        $display("X[1] = %0d + j(%0d)", y1_re, y1_im);
        $display("X[2] = %0d + j(%0d)", y2_re, y2_im);
        $display("X[3] = %0d + j(%0d)", y3_re, y3_im);
        $display("X[4] = %0d + j(%0d)", y4_re, y4_im);
        $display("X[5] = %0d + j(%0d)", y5_re, y5_im);
        $display("X[6] = %0d + j(%0d)", y6_re, y6_im);
        $display("X[7] = %0d + j(%0d)", y7_re, y7_im);

        $display("======================================");

        $finish;

    end

endmodule

fft/fft8.vcd
$version Generated by VerilatedVcd $end
$timescale 1ps $end
 $scope module tb_fft8 $end
  $var wire 1 '! clk $end
  $var wire 1 " reset $end
  $var wire 1 # start $end
  $var wire 16 $ x0 [15:0] $end
  $var wire 16 % x1 [15:0] $end
  $var wire 16 & x2 [15:0] $end
  $var wire 16 ' x3 [15:0] $end
  $var wire 16 ( x4 [15:0] $end
  $var wire 16 ) x5 [15:0] $end
  $var wire 16 * x6 [15:0] $end
  $var wire 16 + x7 [15:0] $end
  $var wire 32 , y0_re [31:0] $end
  $var wire 32 - y1_re [31:0] $end
  $var wire 32 . y2_re [31:0] $end
  $var wire 32 / y3_re [31:0] $end
  $var wire 32 0 y4_re [31:0] $end
  $var wire 32 1 y5_re [31:0] $end
  $var wire 32 2 y6_re [31:0] $end
  $var wire 32 3 y7_re [31:0] $end
  $var wire 32 4 y0_im [31:0] $end
  $var wire 32 5 y1_im [31:0] $end
  $var wire 32 6 y2_im [31:0] $end
  $var wire 32 7 y3_im [31:0] $end
  $var wire 32 8 y4_im [31:0] $end
  $var wire 32 9 y5_im [31:0] $end
  $var wire 32 : y6_im [31:0] $end
  $var wire 32 ; y7_im [31:0] $end
  $var wire 1 < done $end
  $scope module dut $end
   $var wire 1 '! clk $end
   $var wire 1 " reset $end
   $var wire 1 # start $end
   $var wire 16 $ x0 [15:0] $end
   $var wire 16 % x1 [15:0] $end
   $var wire 16 & x2 [15:0] $end
   $var wire 16 ' x3 [15:0] $end
   $var wire 16 ( x4 [15:0] $end
   $var wire 16 ) x5 [15:0] $end
   $var wire 16 * x6 [15:0] $end
   $var wire 16 + x7 [15:0] $end
   $var wire 32 , y0_re [31:0] $end
   $var wire 32 - y1_re [31:0] $end
   $var wire 32 . y2_re [31:0] $end
   $var wire 32 / y3_re [31:0] $end
   $var wire 32 0 y4_re [31:0] $end
   $var wire 32 1 y5_re [31:0] $end
   $var wire 32 2 y6_re [31:0] $end
   $var wire 32 3 y7_re [31:0] $end
   $var wire 32 4 y0_im [31:0] $end
   $var wire 32 5 y1_im [31:0] $end
   $var wire 32 6 y2_im [31:0] $end
   $var wire 32 7 y3_im [31:0] $end
   $var wire 32 8 y4_im [31:0] $end
   $var wire 32 9 y5_im [31:0] $end
   $var wire 32 : y6_im [31:0] $end
   $var wire 32 ; y7_im [31:0] $end
   $var wire 1 < done $end
   $var wire 3 (! IDLE [2:0] $end
   $var wire 3 )! LOAD [2:0] $end
   $var wire 3 *! STAGE1 [2:0] $end
   $var wire 3 +! STAGE2 [2:0] $end
   $var wire 3 ,! STAGE3 [2:0] $end
   $var wire 3 -! OUTPUT [2:0] $end
   $var wire 3 = state [2:0] $end
   $var wire 32 > s0_re[0] [31:0] $end
   $var wire 32 ? s0_re[1] [31:0] $end
   $var wire 32 @ s0_re[2] [31:0] $end
   $var wire 32 A s0_re[3] [31:0] $end
   $var wire 32 B s0_re[4] [31:0] $end
   $var wire 32 C s0_re[5] [31:0] $end
   $var wire 32 D s0_re[6] [31:0] $end
   $var wire 32 E s0_re[7] [31:0] $end
   $var wire 32 F s0_im[0] [31:0] $end
   $var wire 32 G s0_im[1] [31:0] $end
   $var wire 32 H s0_im[2] [31:0] $end
   $var wire 32 I s0_im[3] [31:0] $end
   $var wire 32 J s0_im[4] [31:0] $end
   $var wire 32 K s0_im[5] [31:0] $end
   $var wire 32 L s0_im[6] [31:0] $end
   $var wire 32 M s0_im[7] [31:0] $end
   $var wire 32 N s1_re[0] [31:0] $end
   $var wire 32 O s1_re[1] [31:0] $end
   $var wire 32 P s1_re[2] [31:0] $end
   $var wire 32 Q s1_re[3] [31:0] $end
   $var wire 32 R s1_re[4] [31:0] $end
   $var wire 32 S s1_re[5] [31:0] $end
   $var wire 32 T s1_re[6] [31:0] $end
   $var wire 32 U s1_re[7] [31:0] $end
   $var wire 32 V s1_im[0] [31:0] $end
   $var wire 32 W s1_im[1] [31:0] $end
   $var wire 32 X s1_im[2] [31:0] $end
   $var wire 32 Y s1_im[3] [31:0] $end
   $var wire 32 Z s1_im[4] [31:0] $end
   $var wire 32 [ s1_im[5] [31:0] $end
   $var wire 32 \ s1_im[6] [31:0] $end
   $var wire 32 ] s1_im[7] [31:0] $end
   $var wire 32 ^ s2_re[0] [31:0] $end
   $var wire 32 _ s2_re[1] [31:0] $end
   $var wire 32 ` s2_re[2] [31:0] $end
   $var wire 32 a s2_re[3] [31:0] $end
   $var wire 32 b s2_re[4] [31:0] $end
   $var wire 32 c s2_re[5] [31:0] $end
   $var wire 32 d s2_re[6] [31:0] $end
   $var wire 32 e s2_re[7] [31:0] $end
   $var wire 32 f s2_im[0] [31:0] $end
   $var wire 32 g s2_im[1] [31:0] $end
   $var wire 32 h s2_im[2] [31:0] $end
   $var wire 32 i s2_im[3] [31:0] $end
   $var wire 32 j s2_im[4] [31:0] $end
   $var wire 32 k s2_im[5] [31:0] $end
   $var wire 32 l s2_im[6] [31:0] $end
   $var wire 32 m s2_im[7] [31:0] $end
   $var wire 32 n s3_re[0] [31:0] $end
   $var wire 32 o s3_re[1] [31:0] $end
   $var wire 32 p s3_re[2] [31:0] $end
   $var wire 32 q s3_re[3] [31:0] $end
   $var wire 32 r s3_re[4] [31:0] $end
   $var wire 32 s s3_re[5] [31:0] $end
   $var wire 32 t s3_re[6] [31:0] $end
   $var wire 32 u s3_re[7] [31:0] $end
   $var wire 32 v s3_im[0] [31:0] $end
   $var wire 32 w s3_im[1] [31:0] $end
   $var wire 32 x s3_im[2] [31:0] $end
   $var wire 32 y s3_im[3] [31:0] $end
   $var wire 32 z s3_im[4] [31:0] $end
   $var wire 32 { s3_im[5] [31:0] $end
   $var wire 32 | s3_im[6] [31:0] $end
   $var wire 32 } s3_im[7] [31:0] $end
   $var wire 16 .! W1_RE [15:0] $end
   $var wire 16 /! W1_IM [15:0] $end
   $var wire 16 0! W2_RE [15:0] $end
   $var wire 16 1! W2_IM [15:0] $end
   $var wire 16 /! W3_RE [15:0] $end
   $var wire 16 /! W3_IM [15:0] $end
   $var wire 64 ~ mult_re [63:0] $end
   $var wire 64 "! mult_im [63:0] $end
   $var wire 32 $! tw_re [31:0] $end
   $var wire 32 %! tw_im [31:0] $end
   $var wire 32 &! i [31:0] $end
  $upscope $end
 $upscope $end
$enddefinitions $end


#0
1"
0#
b0000000000000001 $
b0000000000000000 %
b0000000000000000 &
b0000000000000000 '
b0000000000000000 (
b0000000000000000 )
b0000000000000000 *
b0000000000000000 +
b00000000000000000000000000000000 ,
b00000000000000000000000000000000 -
b00000000000000000000000000000000 .
b00000000000000000000000000000000 /
b00000000000000000000000000000000 0
b00000000000000000000000000000000 1
b00000000000000000000000000000000 2
b00000000000000000000000000000000 3
b00000000000000000000000000000000 4
b00000000000000000000000000000000 5
b00000000000000000000000000000000 6
b00000000000000000000000000000000 7
b00000000000000000000000000000000 8
b00000000000000000000000000000000 9
b00000000000000000000000000000000 :
b00000000000000000000000000000000 ;
0<
b000 =
b00000000000000000000000000000000 >
b00000000000000000000000000000000 ?
b00000000000000000000000000000000 @
b00000000000000000000000000000000 A
b00000000000000000000000000000000 B
b00000000000000000000000000000000 C
b00000000000000000000000000000000 D
b00000000000000000000000000000000 E
b00000000000000000000000000000000 F
b00000000000000000000000000000000 G
b00000000000000000000000000000000 H
b00000000000000000000000000000000 I
b00000000000000000000000000000000 J
b00000000000000000000000000000000 K
b00000000000000000000000000000000 L
b00000000000000000000000000000000 M
b00000000000000000000000000000000 N
b00000000000000000000000000000000 O
b00000000000000000000000000000000 P
b00000000000000000000000000000000 Q
b00000000000000000000000000000000 R
b00000000000000000000000000000000 S
b00000000000000000000000000000000 T
b00000000000000000000000000000000 U
b00000000000000000000000000000000 V
b00000000000000000000000000000000 W
b00000000000000000000000000000000 X
b00000000000000000000000000000000 Y
b00000000000000000000000000000000 Z
b00000000000000000000000000000000 [
b00000000000000000000000000000000 \
b00000000000000000000000000000000 ]
b00000000000000000000000000000000 ^
b00000000000000000000000000000000 _
b00000000000000000000000000000000 `
b00000000000000000000000000000000 a
b00000000000000000000000000000000 b
b00000000000000000000000000000000 c
b00000000000000000000000000000000 d
b00000000000000000000000000000000 e
b00000000000000000000000000000000 f
b00000000000000000000000000000000 g
b00000000000000000000000000000000 h
b00000000000000000000000000000000 i
b00000000000000000000000000000000 j
b00000000000000000000000000000000 k
b00000000000000000000000000000000 l
b00000000000000000000000000000000 m
b00000000000000000000000000000000 n
b00000000000000000000000000000000 o
b00000000000000000000000000000000 p
b00000000000000000000000000000000 q
b00000000000000000000000000000000 r
b00000000000000000000000000000000 s
b00000000000000000000000000000000 t
b00000000000000000000000000000000 u
b00000000000000000000000000000000 v
b00000000000000000000000000000000 w
b00000000000000000000000000000000 x
b00000000000000000000000000000000 y
b00000000000000000000000000000000 z
b00000000000000000000000000000000 {
b00000000000000000000000000000000 |
b00000000000000000000000000000000 }
b0000000000000000000000000000000000000000000000000000000000000000 ~
b0000000000000000000000000000000000000000000000000000000000000000 "!
b00000000000000000000000000000000 $!
b00000000000000000000000000000000 %!
b00000000000000000000000000000000 &!
0'!
b000 (!
b001 )!
b010 *!
b011 +!
b100 ,!
b101 -!
b0101101010000010 .!
b1010010101111110 /!
b0000000000000000 0!
b1000000000000001 1!
#5000
b00000000000000000000000000001000 &!
1'!
#10000
0'!
#15000
1'!
#20000
0"
0'!
#25000
1'!
#30000
1#
0'!
#35000
b001 =
1'!
#40000
0#
0'!
#45000
b010 =
b00000000000000000000000000000001 >
1'!
#50000
0'!
#55000
b011 =
b00000000000000000000000000000001 N
b00000000000000000000000000000001 O
1'!
#60000
0'!
#65000
b100 =
b00000000000000000000000000000001 ^
b00000000000000000000000000000001 _
b00000000000000000000000000000001 `
b00000000000000000000000000000001 a
1'!
#70000
0'!
#75000
b101 =
b00000000000000000000000000000001 n
b00000000000000000000000000000001 o
b00000000000000000000000000000001 p
b00000000000000000000000000000001 q
b00000000000000000000000000000001 r
b00000000000000000000000000000001 s
b00000000000000000000000000000001 t
b00000000000000000000000000000001 u
1'!
#80000
0'!
#85000
b00000000000000000000000000000001 ,
b00000000000000000000000000000001 -
b00000000000000000000000000000001 .
b00000000000000000000000000000001 /
b00000000000000000000000000000001 0
b00000000000000000000000000000001 1
b00000000000000000000000000000001 2
b00000000000000000000000000000001 3
1<
b000 =
1'!
#90000
0'!
#95000
0<
1'!
