risc_dev/rv32i_core.v
`timescale 1ns/1ps

module rv32i_core (
    input  wire        clk,
    input  wire        reset,

    // Instruction memory interface
    output wire [31:0] imem_addr,
    input  wire [31:0] imem_rdata,

    // Data memory interface
    output reg         dmem_valid,
    output reg         dmem_write,
    output reg  [31:0] dmem_addr,
    output reg  [31:0] dmem_wdata,
    output reg  [3:0]  dmem_wstrb,

    input  wire [31:0] dmem_rdata,
    input  wire         dmem_ready
);

    // ============================================================
    // Program Counter
    // ============================================================

    reg [31:0] pc;

    assign imem_addr = pc;


    // ============================================================
    // Register File
    // x0 is always zero
    // ============================================================

    reg [31:0] regs [0:31];

    wire [4:0] rs1 = imem_rdata[19:15];
    wire [4:0] rs2 = imem_rdata[24:20];
    wire [4:0] rd  = imem_rdata[11:7];

    wire [31:0] rs1_data =
        (rs1 == 5'd0) ? 32'd0 : regs[rs1];

    wire [31:0] rs2_data =
        (rs2 == 5'd0) ? 32'd0 : regs[rs2];


    // ============================================================
    // Instruction fields
    // ============================================================

    wire [6:0] opcode = imem_rdata[6:0];
    wire [2:0] funct3 = imem_rdata[14:12];
    wire [6:0] funct7 = imem_rdata[31:25];


    // ============================================================
    // Immediate generation
    // ============================================================

    wire [31:0] imm_I =
        {{20{imem_rdata[31]}},
         imem_rdata[31:20]};

    wire [31:0] imm_S =
        {{20{imem_rdata[31]}},
         imem_rdata[31:25],
         imem_rdata[11:7]};

    wire [31:0] imm_B =
        {{19{imem_rdata[31]}},
         imem_rdata[31],
         imem_rdata[7],
         imem_rdata[30:25],
         imem_rdata[11:8],
         1'b0};

    wire [31:0] imm_U =
        {imem_rdata[31:12], 12'b0};

    wire [31:0] imm_J =
        {{11{imem_rdata[31]}},
         imem_rdata[31],
         imem_rdata[19:12],
         imem_rdata[20],
         imem_rdata[30:21],
         1'b0};


    // ============================================================
    // Opcodes
    // ============================================================

    localparam OPCODE_LUI    = 7'b0110111;
    localparam OPCODE_AUIPC  = 7'b0010111;
    localparam OPCODE_JAL    = 7'b1101111;
    localparam OPCODE_JALR   = 7'b1100111;
    localparam OPCODE_BRANCH = 7'b1100011;
    localparam OPCODE_LOAD   = 7'b0000011;
    localparam OPCODE_STORE  = 7'b0100011;
    localparam OPCODE_OP_IMM = 7'b0010011;
    localparam OPCODE_OP     = 7'b0110011;


    // ============================================================
    // ALU
    // ============================================================

    reg [31:0] alu_result;

    always @(*) begin

        alu_result = 32'd0;

        case (opcode)

            // ----------------------------------------------------
            // ADDI
            // ----------------------------------------------------

            OPCODE_OP_IMM: begin

                case (funct3)

                    3'b000: begin
                        alu_result = rs1_data + imm_I;
                    end

                    // ANDI
                    3'b111: begin
                        alu_result = rs1_data & imm_I;
                    end

                    // ORI
                    3'b110: begin
                        alu_result = rs1_data | imm_I;
                    end

                    // XORI
                    3'b100: begin
                        alu_result = rs1_data ^ imm_I;
                    end

                    default: begin
                        alu_result = 32'd0;
                    end

                endcase
            end


            // ----------------------------------------------------
            // ADD / SUB / AND / OR / XOR
            // ----------------------------------------------------

            OPCODE_OP: begin

                case (funct3)

                    3'b000: begin

                        if (funct7 == 7'b0100000)
                            alu_result = rs1_data - rs2_data;
                        else
                            alu_result = rs1_data + rs2_data;

                    end

                    3'b111:
                        alu_result = rs1_data & rs2_data;

                    3'b110:
                        alu_result = rs1_data | rs2_data;

                    3'b100:
                        alu_result = rs1_data ^ rs2_data;

                    default:
                        alu_result = 32'd0;

                endcase
            end


            // ----------------------------------------------------
            // LUI
            // ----------------------------------------------------

            OPCODE_LUI: begin
                alu_result = imm_U;
            end


            // ----------------------------------------------------
            // AUIPC
            // ----------------------------------------------------

            OPCODE_AUIPC: begin
                alu_result = pc + imm_U;
            end


            // ----------------------------------------------------
            // LOAD
            // ----------------------------------------------------

            OPCODE_LOAD: begin
                alu_result = rs1_data + imm_I;
            end


            // ----------------------------------------------------
            // STORE
            // ----------------------------------------------------

            OPCODE_STORE: begin
                alu_result = rs1_data + imm_S;
            end


            default: begin
                alu_result = 32'd0;
            end

        endcase

    end


    // ============================================================
    // Sequential CPU
    // ============================================================

    integer i;

    always @(posedge clk) begin

        if (reset) begin

            pc <= 32'h00000000;

            dmem_valid <= 1'b0;
            dmem_write <= 1'b0;
            dmem_addr  <= 32'd0;
            dmem_wdata <= 32'd0;
            dmem_wstrb <= 4'b0000;

            for (i = 0; i < 32; i = i + 1)
                regs[i] <= 32'd0;

        end

        else begin

            // x0 must always remain zero
            regs[0] <= 32'd0;

            // Default memory signals
            dmem_valid <= 1'b0;
            dmem_write <= 1'b0;
            dmem_wstrb <= 4'b0000;


            case (opcode)

                // =================================================
                // LUI
                // =================================================

                OPCODE_LUI: begin

                    if (rd != 0)
                        regs[rd] <= imm_U;

                    pc <= pc + 32'd4;

                end


                // =================================================
                // AUIPC
                // =================================================

                OPCODE_AUIPC: begin

                    if (rd != 0)
                        regs[rd] <= pc + imm_U;

                    pc <= pc + 32'd4;

                end


                // =================================================
                // OP-IMM
                // =================================================

                OPCODE_OP_IMM: begin

                    if (rd != 0)
                        regs[rd] <= alu_result;

                    pc <= pc + 32'd4;

                end


                // =================================================
                // OP
                // =================================================

                OPCODE_OP: begin

                    if (rd != 0)
                        regs[rd] <= alu_result;

                    pc <= pc + 32'd4;

                end


                // =================================================
                // LOAD
                // =================================================

                OPCODE_LOAD: begin

                    dmem_valid <= 1'b1;
                    dmem_write <= 1'b0;
                    dmem_addr  <= alu_result;

                    if (dmem_ready) begin

                        if (rd != 0)
                            regs[rd] <= dmem_rdata;

                        pc <= pc + 32'd4;

                    end

                end


                // =================================================
                // STORE
                // =================================================

                OPCODE_STORE: begin

                    dmem_valid <= 1'b1;
                    dmem_write <= 1'b1;
                    dmem_addr  <= alu_result;
                    dmem_wdata <= rs2_data;
                    dmem_wstrb <= 4'b1111;

                    if (dmem_ready) begin
                        pc <= pc + 32'd4;
                    end

                end


                // =================================================
                // BEQ / BNE
                // =================================================

                OPCODE_BRANCH: begin

                    case (funct3)

                        // BEQ
                        3'b000: begin

                            if (rs1_data == rs2_data)
                                pc <= pc + imm_B;
                            else
                                pc <= pc + 32'd4;

                        end

                        // BNE
                        3'b001: begin

                            if (rs1_data != rs2_data)
                                pc <= pc + imm_B;
                            else
                                pc <= pc + 32'd4;

                        end

                        default:
                            pc <= pc + 32'd4;

                    endcase

                end


                // =================================================
                // JAL
                // =================================================

                OPCODE_JAL: begin

                    if (rd != 0)
                        regs[rd] <= pc + 32'd4;

                    pc <= pc + imm_J;

                end


                // =================================================
                // JALR
                // =================================================

                OPCODE_JALR: begin

                    if (rd != 0)
                        regs[rd] <= pc + 32'd4;

                    pc <= (rs1_data + imm_I) & 32'hFFFFFFFE;

                end


                // =================================================
                // Unknown instruction
                // =================================================

                default: begin

                    pc <= pc + 32'd4;

                end

            endcase

        end

    end

endmodule

risc_dev/tb_rv32i_core.v
`timescale 1ns/1ps

module tb_rv32i_core;

    reg clk;
    reg reset;

    wire [31:0] imem_addr;
    reg  [31:0] imem_rdata;

    wire        dmem_valid;
    wire        dmem_write;
    wire [31:0] dmem_addr;
    wire [31:0] dmem_wdata;
    wire [3:0]  dmem_wstrb;

    reg [31:0] dmem_rdata;
    reg        dmem_ready;


    // ============================================================
    // CPU
    // ============================================================

    rv32i_core dut (

        .clk(clk),
        .reset(reset),

        .imem_addr(imem_addr),
        .imem_rdata(imem_rdata),

        .dmem_valid(dmem_valid),
        .dmem_write(dmem_write),
        .dmem_addr(dmem_addr),
        .dmem_wdata(dmem_wdata),
        .dmem_wstrb(dmem_wstrb),

        .dmem_rdata(dmem_rdata),
        .dmem_ready(dmem_ready)

    );


    // ============================================================
    // Clock
    // ============================================================

    always #5 clk = ~clk;


    // ============================================================
    // Instruction Memory
    // ============================================================

    always @(*) begin

        case (imem_addr)

            // ADDI x1, x0, 10
            32'h00000000:
                imem_rdata = 32'h00A00093;

            // ADDI x2, x0, 20
            32'h00000004:
                imem_rdata = 32'h01400113;

            // ADD x3, x1, x2
            32'h00000008:
                imem_rdata = 32'h002081B3;

            // SUB x4, x3, x1
            32'h0000000C:
                imem_rdata = 32'h40118233;

            // AND x5, x1, x2
            32'h00000010:
                imem_rdata = 32'h0020F2B3;

            // OR x6, x1, x2
            32'h00000014:
                imem_rdata = 32'h0020E333;

            // XOR x7, x1, x2
            32'h00000018:
                imem_rdata = 32'h0020C3B3;

            // Infinite loop:
            // BEQ x0, x0, 0
            32'h0000001C:
                imem_rdata = 32'h00000063;

            default:
                imem_rdata = 32'h00000013; // NOP = ADDI x0,x0,0

        endcase

    end


    // ============================================================
    // Simple Data Memory
    // ============================================================

    assign dmem_rdata = 32'h00000000;
    assign dmem_ready = 1'b1;


    // ============================================================
    // Simulation
    // ============================================================

    initial begin

        $dumpfile("rv32i_core.vcd");
        $dumpvars(0, tb_rv32i_core);

        clk = 1'b0;
        reset = 1'b1;

        #20;

        reset = 1'b0;

        #200;

        $display("----------------------------------");
        $display("RV32I simulation finished");
        $display("----------------------------------");

        $display("x1 = %d", dut.regs[1]);
        $display("x2 = %d", dut.regs[2]);
        $display("x3 = %d", dut.regs[3]);
        $display("x4 = %d", dut.regs[4]);
        $display("x5 = %d", dut.regs[5]);
        $display("x6 = %d", dut.regs[6]);
        $display("x7 = %d", dut.regs[7]);

        $finish;

    end

endmodule

risc_dev/rv32i_core.vcd
$version Generated by VerilatedVcd $end
$timescale 1ps $end
 $scope module tb_rv32i_core $end
  $var wire 1 X clk $end
  $var wire 1 Y reset $end
  $var wire 32 " imem_addr [31:0] $end
  $var wire 32 # imem_rdata [31:0] $end
  $var wire 1 $ dmem_valid $end
  $var wire 1 % dmem_write $end
  $var wire 32 & dmem_addr [31:0] $end
  $var wire 32 ' dmem_wdata [31:0] $end
  $var wire 4 ( dmem_wstrb [3:0] $end
  $var wire 32 Z dmem_rdata [31:0] $end
  $var wire 1 [ dmem_ready $end
  $scope module dut $end
   $var wire 1 X clk $end
   $var wire 1 Y reset $end
   $var wire 32 " imem_addr [31:0] $end
   $var wire 32 # imem_rdata [31:0] $end
   $var wire 1 $ dmem_valid $end
   $var wire 1 % dmem_write $end
   $var wire 32 & dmem_addr [31:0] $end
   $var wire 32 ' dmem_wdata [31:0] $end
   $var wire 4 ( dmem_wstrb [3:0] $end
   $var wire 32 Z dmem_rdata [31:0] $end
   $var wire 1 [ dmem_ready $end
   $var wire 32 " pc [31:0] $end
   $var wire 32 ) regs[0] [31:0] $end
   $var wire 32 * regs[1] [31:0] $end
   $var wire 32 + regs[2] [31:0] $end
   $var wire 32 , regs[3] [31:0] $end
   $var wire 32 - regs[4] [31:0] $end
   $var wire 32 . regs[5] [31:0] $end
   $var wire 32 / regs[6] [31:0] $end
   $var wire 32 0 regs[7] [31:0] $end
   $var wire 32 1 regs[8] [31:0] $end
   $var wire 32 2 regs[9] [31:0] $end
   $var wire 32 3 regs[10] [31:0] $end
   $var wire 32 4 regs[11] [31:0] $end
   $var wire 32 5 regs[12] [31:0] $end
   $var wire 32 6 regs[13] [31:0] $end
   $var wire 32 7 regs[14] [31:0] $end
   $var wire 32 8 regs[15] [31:0] $end
   $var wire 32 9 regs[16] [31:0] $end
   $var wire 32 : regs[17] [31:0] $end
   $var wire 32 ; regs[18] [31:0] $end
   $var wire 32 < regs[19] [31:0] $end
   $var wire 32 = regs[20] [31:0] $end
   $var wire 32 > regs[21] [31:0] $end
   $var wire 32 ? regs[22] [31:0] $end
   $var wire 32 @ regs[23] [31:0] $end
   $var wire 32 A regs[24] [31:0] $end
   $var wire 32 B regs[25] [31:0] $end
   $var wire 32 C regs[26] [31:0] $end
   $var wire 32 D regs[27] [31:0] $end
   $var wire 32 E regs[28] [31:0] $end
   $var wire 32 F regs[29] [31:0] $end
   $var wire 32 G regs[30] [31:0] $end
   $var wire 32 H regs[31] [31:0] $end
   $var wire 5 I rs1 [4:0] $end
   $var wire 5 J rs2 [4:0] $end
   $var wire 5 K rd [4:0] $end
   $var wire 32 L rs1_data [31:0] $end
   $var wire 32 M rs2_data [31:0] $end
   $var wire 7 N opcode [6:0] $end
   $var wire 3 O funct3 [2:0] $end
   $var wire 7 P funct7 [6:0] $end
   $var wire 32 Q imm_I [31:0] $end
   $var wire 32 R imm_S [31:0] $end
   $var wire 32 S imm_B [31:0] $end
   $var wire 32 T imm_U [31:0] $end
   $var wire 32 U imm_J [31:0] $end
   $var wire 7 \ OPCODE_LUI [6:0] $end
   $var wire 7 ] OPCODE_AUIPC [6:0] $end
   $var wire 7 ^ OPCODE_JAL [6:0] $end
   $var wire 7 _ OPCODE_JALR [6:0] $end
   $var wire 7 ` OPCODE_BRANCH [6:0] $end
   $var wire 7 a OPCODE_LOAD [6:0] $end
   $var wire 7 b OPCODE_STORE [6:0] $end
   $var wire 7 c OPCODE_OP_IMM [6:0] $end
   $var wire 7 d OPCODE_OP [6:0] $end
   $var wire 32 V alu_result [31:0] $end
   $var wire 32 W i [31:0] $end
  $upscope $end
 $upscope $end
$enddefinitions $end


#0
b00000000000000000000000000000000 "
b00000000101000000000000010010011 #
0$
0%
b00000000000000000000000000000000 &
b00000000000000000000000000000000 '
b0000 (
b00000000000000000000000000000000 )
b00000000000000000000000000000000 *
b00000000000000000000000000000000 +
b00000000000000000000000000000000 ,
b00000000000000000000000000000000 -
b00000000000000000000000000000000 .
b00000000000000000000000000000000 /
b00000000000000000000000000000000 0
b00000000000000000000000000000000 1
b00000000000000000000000000000000 2
b00000000000000000000000000000000 3
b00000000000000000000000000000000 4
b00000000000000000000000000000000 5
b00000000000000000000000000000000 6
b00000000000000000000000000000000 7
b00000000000000000000000000000000 8
b00000000000000000000000000000000 9
b00000000000000000000000000000000 :
b00000000000000000000000000000000 ;
b00000000000000000000000000000000 <
b00000000000000000000000000000000 =
b00000000000000000000000000000000 >
b00000000000000000000000000000000 ?
b00000000000000000000000000000000 @
b00000000000000000000000000000000 A
b00000000000000000000000000000000 B
b00000000000000000000000000000000 C
b00000000000000000000000000000000 D
b00000000000000000000000000000000 E
b00000000000000000000000000000000 F
b00000000000000000000000000000000 G
b00000000000000000000000000000000 H
b00000 I
b01010 J
b00001 K
b00000000000000000000000000000000 L
b00000000000000000000000000000000 M
b0010011 N
b000 O
b0000000 P
b00000000000000000000000000001010 Q
b00000000000000000000000000000001 R
b00000000000000000000100000000000 S
b00000000101000000000000000000000 T
b00000000000000000000000000001010 U
b00000000000000000000000000001010 V
b00000000000000000000000000000000 W
0X
1Y
b00000000000000000000000000000000 Z
1[
b0110111 \
b0010111 ]
b1101111 ^
b1100111 _
b1100011 `
b0000011 a
b0100011 b
b0010011 c
b0110011 d
#5000
b00000000000000000000000000100000 W
1X
#10000
0X
#15000
1X
#20000
0X
0Y
#25000
b00000000000000000000000000000100 "
b00000001010000000000000100010011 #
b00000000000000000000000000001010 *
b10100 J
b00010 K
b00000000000000000000000000010100 Q
b00000000000000000000000000000010 R
b00000000000000000000000000000010 S
b00000001010000000000000000000000 T
b00000000000000000000000000010100 U
b00000000000000000000000000010100 V
1X
#30000
0X
#35000
b00000000000000000000000000001000 "
b00000000001000001000000110110011 #
b00000000000000000000000000010100 +
b00001 I
b00010 J
b00011 K
b00000000000000000000000000001010 L
b00000000000000000000000000010100 M
b0110011 N
b00000000000000000000000000000010 Q
b00000000000000000000000000000011 R
b00000000000000000000100000000010 S
b00000000001000001000000000000000 T
b00000000000000001000000000000010 U
b00000000000000000000000000011110 V
1X
#40000
0X
#45000
b00000000000000000000000000001100 "
b01000000000100011000001000110011 #
b00000000000000000000000000011110 ,
b00011 I
b00001 J
b00100 K
b00000000000000000000000000011110 L
b00000000000000000000000000001010 M
b0100000 P
b00000000000000000000010000000001 Q
b00000000000000000000010000000100 R
b00000000000000000000010000000100 S
b01000000000100011000000000000000 T
b00000000000000011000110000000000 U
b00000000000000000000000000010100 V
1X
#50000
0X
#55000
b00000000000000000000000000010000 "
b00000000001000001111001010110011 #
b00000000000000000000000000010100 -
b00001 I
b00010 J
b00101 K
b00000000000000000000000000001010 L
b00000000000000000000000000010100 M
b111 O
b0000000 P
b00000000000000000000000000000010 Q
b00000000000000000000000000000101 R
b00000000000000000000100000000100 S
b00000000001000001111000000000000 T
b00000000000000001111000000000010 U
b00000000000000000000000000000000 V
1X
#60000
0X
#65000
b00000000000000000000000000010100 "
b00000000001000001110001100110011 #
b00110 K
b110 O
b00000000000000000000000000000110 R
b00000000000000000000000000000110 S
b00000000001000001110000000000000 T
b00000000000000001110000000000010 U
b00000000000000000000000000011110 V
1X
#70000
0X
#75000
b00000000000000000000000000011000 "
b00000000001000001100001110110011 #
b00000000000000000000000000011110 /
b00111 K
b100 O
b00000000000000000000000000000111 R
b00000000000000000000100000000110 S
b00000000001000001100000000000000 T
b00000000000000001100000000000010 U
1X
#80000
0X
#85000
b00000000000000000000000000011100 "
b00000000000000000000000001100011 #
b00000000000000000000000000011110 0
b00000 I
b00000 J
b00000 K
b00000000000000000000000000000000 L
b00000000000000000000000000000000 M
b1100011 N
b000 O
b00000000000000000000000000000000 Q
b00000000000000000000000000000000 R
b00000000000000000000000000000000 S
b00000000000000000000000000000000 T
b00000000000000000000000000000000 U
b00000000000000000000000000000000 V
1X
